{
  "entityType" : "NOTIFICATION_RULE",
  "entity" : {
    "additionalConfig" : {
      "description" : "Send notification to tenant admins when an alarm is created"
    },
    "enabled" : true,
    "externalId" : null,
    "id" : {
      "entityType" : "NOTIFICATION_RULE",
      "id" : "60cd14c0-81fc-11f0-b4e8-c3dcfa6424a6"
    },
    "name" : "New alarm",
    "recipientsConfig" : {
      "escalationTable" : {
        "0" : [ "60caa3c0-81fc-11f0-b4e8-c3dcfa6424a6" ]
      },
      "triggerType" : "ALARM"
    },
    "templateId" : {
      "entityType" : "NOTIFICATION_TEMPLATE",
      "id" : "60cbdc40-81fc-11f0-b4e8-c3dcfa6424a6"
    },
    "triggerConfig" : {
      "triggerType" : "ALARM",
      "alarmSeverities" : null,
      "alarmTypes" : null,
      "clearRule" : null,
      "notifyOn" : [ "CREATED" ],
      "triggerType" : "ALARM"
    },
    "triggerType" : "ALARM"
  }
}